{"name":"Verify working of JS Alerts","id":"javascript-alerts-tests;verify-working-of-js-alerts","scenarioId":"frontend/js-alert:Verify working of JS Alerts","methodName":"Verify working of JS Alerts","testSteps":[{"number":1,"description":"Given I am on the JavaScript alerts page","duration":19881,"startTime":"2023-12-24T15:13:14.993110893Z[Etc/UTC]","screenshots":[{"screenshot":"9706b0dfe29e72cb4a5c6939e9913c3742bb5a42090bd2d4897b63e86c7e8565.png","timeStamp":1703430814874,"screenshotName":"9706b0dfe29e72cb4a5c6939e9913c3742bb5a42090bd2d4897b63e86c7e8565.png"}],"result":"SUCCESS","precondition":false,"level":0},{"number":2,"description":"When I click the JS Alert button of alert","duration":2126,"startTime":"2023-12-24T15:13:35.301682119Z[Etc/UTC]","screenshots":[{"screenshot":"9706b0dfe29e72cb4a5c6939e9913c3742bb5a42090bd2d4897b63e86c7e8565.png","timeStamp":1703430815672,"screenshotName":"9706b0dfe29e72cb4a5c6939e9913c3742bb5a42090bd2d4897b63e86c7e8565.png"}],"result":"SUCCESS","precondition":false,"level":0},{"number":3,"description":"Then I interact as OK with the alert","duration":1514,"startTime":"2023-12-24T15:13:37.429505307Z[Etc/UTC]","screenshots":[{"screenshot":"a5ac5d0b70c370d37ea938c301bf21573ecb419bfa41569a4993423a8f5afa6a.png","timeStamp":1703430818944,"screenshotName":"a5ac5d0b70c370d37ea938c301bf21573ecb419bfa41569a4993423a8f5afa6a.png"}],"result":"SUCCESS","precondition":false,"level":0},{"number":4,"description":"And Result says You successfully clicked an alert","duration":372,"startTime":"2023-12-24T15:13:38.945993425Z[Etc/UTC]","screenshots":[{"screenshot":"a5ac5d0b70c370d37ea938c301bf21573ecb419bfa41569a4993423a8f5afa6a.png","timeStamp":1703430818958,"screenshotName":"a5ac5d0b70c370d37ea938c301bf21573ecb419bfa41569a4993423a8f5afa6a.png"}],"result":"SUCCESS","precondition":false,"level":0}],"userStory":{"id":"frontend/js-alert","storyName":"JavaScript Alerts Tests","displayName":"JavaScript Alerts Tests","path":"frontend/js-alert","pathElements":[{"name":"frontend","description":""},{"name":"js-alert","description":""}],"type":"feature"},"title":"Verify working of JS Alerts","description":"","tags":[{"name":"Linux","type":"context","displayName":"Linux"},{"name":"Chrome","type":"context","displayName":"Chrome"},{"name":"fork 1","type":"test fork","displayName":"fork 1"},{"name":"herokuapp","type":"tag","displayName":"herokuapp"},{"name":"Chrome, Linux","type":"context","displayName":"Chrome, Linux"},{"name":"test","type":"tag","displayName":"test"},{"name":"frontend","type":"tag","displayName":"frontend"}],"startTime":"2023-12-24T15:13:13.233901152Z[Etc/UTC]","duration":21242,"projectKey":"","sessionId":"77db4cee9e0136d0318d03d553ca67b1","driver":"chrome","isManualTestingUpToDate":false,"context":"chrome,linux","manual":false,"testSource":"Cucumber","order":0,"result":"SUCCESS"}