{"name":"Write Text In An iFrame","id":"frames-tests;write-text-in-an-iframe","scenarioId":"frontend/frames:Write Text In An iFrame","methodName":"Write Text In An iFrame","testSteps":[{"number":1,"description":"Given I am on the frames page","duration":18886,"startTime":"2023-12-24T15:13:15.711372961Z[Etc/UTC]","screenshots":[{"screenshot":"e891438a2096294cd570c51496c517ed23bcbf28f23c759d7b4700d31131fe56.png","timeStamp":1703430814597,"screenshotName":"e891438a2096294cd570c51496c517ed23bcbf28f23c759d7b4700d31131fe56.png"}],"result":"SUCCESS","precondition":false,"level":0},{"number":2,"description":"When I navigate to iFrame page","duration":2397,"startTime":"2023-12-24T15:13:34.897439677Z[Etc/UTC]","screenshots":[{"screenshot":"58ca61c6efa381ff5c0e4c6cb8c9f229029126a7d79aa18d73d66d64577a0895.png","timeStamp":1703430817294,"screenshotName":"58ca61c6efa381ff5c0e4c6cb8c9f229029126a7d79aa18d73d66d64577a0895.png"}],"result":"SUCCESS","precondition":false,"level":0},{"number":3,"description":"Then I write Kotlin Automation Framework in iframe","duration":1790,"startTime":"2023-12-24T15:13:37.295666208Z[Etc/UTC]","screenshots":[{"screenshot":"32bbd5ed9fce9a39442795103663bc012f56e1a0bcaa636d47ef9b8d04224acf.png","timeStamp":1703430819086,"screenshotName":"32bbd5ed9fce9a39442795103663bc012f56e1a0bcaa636d47ef9b8d04224acf.png"}],"result":"SUCCESS","precondition":false,"level":0},{"number":4,"description":"And iframe has the text Kotlin Automation Framework","duration":609,"startTime":"2023-12-24T15:13:39.087274732Z[Etc/UTC]","screenshots":[{"screenshot":"32bbd5ed9fce9a39442795103663bc012f56e1a0bcaa636d47ef9b8d04224acf.png","timeStamp":1703430819090,"screenshotName":"32bbd5ed9fce9a39442795103663bc012f56e1a0bcaa636d47ef9b8d04224acf.png"}],"result":"SUCCESS","precondition":false,"level":0}],"userStory":{"id":"frontend/frames","storyName":"Frames Tests","displayName":"Frames Tests","path":"frontend/frames","pathElements":[{"name":"frontend","description":""},{"name":"frames","description":""}],"type":"feature"},"title":"Write Text In An iFrame","description":"","tags":[{"name":"Linux","type":"context","displayName":"Linux"},{"name":"Chrome","type":"context","displayName":"Chrome"},{"name":"herokuapp","type":"tag","displayName":"herokuapp"},{"name":"Chrome, Linux","type":"context","displayName":"Chrome, Linux"},{"name":"test","type":"tag","displayName":"test"},{"name":"fork 4","type":"test fork","displayName":"fork 4"},{"name":"frontend","type":"tag","displayName":"frontend"}],"startTime":"2023-12-24T15:13:13.399054718Z[Etc/UTC]","duration":20856,"projectKey":"","sessionId":"35c760523c49af674a9e274783205969","driver":"chrome","isManualTestingUpToDate":false,"context":"chrome,linux","manual":false,"testSource":"Cucumber","order":0,"result":"SUCCESS"}